indobenchmark/__init__.py
indobenchmark/tokenization_indonlg.py
indobenchmark/version.py
indobenchmark_toolkit-0.1.7.dist-info/LICENSE
indobenchmark_toolkit-0.1.7.dist-info/METADATA
indobenchmark_toolkit-0.1.7.dist-info/WHEEL
indobenchmark_toolkit-0.1.7.dist-info/top_level.txt
indobenchmark_toolkit-0.1.7.dist-info/RECORD
