Metadata-Version: 2.1
Name: indobenchmark-toolkit
Version: 0.1.7
Summary: Indobenchmark toolkit for supporting IndoNLU and IndoNLG
Home-page: https://github.com/SamuelCahyawijaya/indobenchmark-toolkit
Author: Samuel Cahyawijaya
Author-email: samuel.cahyawijaya@gmail.com
Project-URL: Bug Tracker, https://github.com/SamuelCahyawijaya/indobenchmark-toolkit/issues
Classifier: Programming Language :: Python :: 3
Classifier: License :: OSI Approved :: MIT License
Classifier: Operating System :: OS Independent
Requires-Python: >=3.6
License-File: LICENSE
Requires-Dist: transformers (>=4.3.2)
Requires-Dist: sentencepiece (>=0.1.95)
Requires-Dist: datasets (>=1.4.1)
Requires-Dist: torch (>=1.7.1)
